{
  "algorithm_version": 2,
  "end_time": "Tue, 25 Jul 2023 01:32:28 GMT",
  "grade": "F",
  "hidden": false,
  "likelihood_indicator": "MEDIUM",
  "response_headers": {
    "Access-Control-Allow-Origin": "*",
    "Cache-Control": "public, max-age=3580",
    "Connection": "keep-alive",
    "Content-Encoding": "gzip",
    "Content-Length": "16963",
    "Content-Type": "text/html;charset=UTF-8",
    "Date": "Tue, 25 Jul 2023 01:32:09 GMT",
    "Expires": "Tue, 25 Jul 2023 02:31:49 GMT",
    "Last-Modified": "Tue, 25 Jul 2023 01:32:09 GMT",
    "Server": "Apache",
    "Server-Timing": "cdn-cache; desc=HIT, edge; dur=38, origin; dur=0, ak_p; desc=\"469513_3088711197_608906373_4659_6261_9_-_-\";dur=1",
    "Surrogate-Control": "no-store",
    "Vary": "Accept-Encoding",
    "X-Akamai-Transformed": "9 20714 0 pmb=mRUM,1",
    "X-Frame-Options": "SAMEORIGIN"
  },
  "scan_id": 40082008,
  "score": 0,
  "start_time": "Tue, 25 Jul 2023 01:26:49 GMT",
  "state": "FINISHED",
  "status_code": 200,
  "tests_failed": 5,
  "tests_passed": 7,
  "tests_quantity": 12
}