{
  "algorithm_version": 2,
  "end_time": "Tue, 23 Jan 2024 00:57:44 GMT",
  "grade": "F",
  "hidden": false,
  "likelihood_indicator": "MEDIUM",
  "response_headers": {
    "Access-Control-Allow-Origin": "*",
    "Cache-Control": "public, max-age=3566",
    "Connection": "keep-alive",
    "Content-Encoding": "gzip",
    "Content-Length": "19934",
    "Content-Type": "text/html;charset=UTF-8",
    "Date": "Tue, 23 Jan 2024 00:57:39 GMT",
    "Expires": "Tue, 23 Jan 2024 01:57:05 GMT",
    "Last-Modified": "Tue, 23 Jan 2024 00:57:39 GMT",
    "Server": "Apache",
    "Server-Timing": "cdn-cache; desc=REVALIDATE, edge; dur=210, origin; dur=289, ak_p; desc=\"1705971459193_399222608_1066646434_49840_4313_6_0_-\";dur=1",
    "Surrogate-Control": "no-store",
    "Vary": "Accept-Encoding",
    "X-Akamai-Transformed": "9 24510 0 pmb=mRUM,1",
    "X-Frame-Options": "SAMEORIGIN"
  },
  "scan_id": 46893136,
  "score": 0,
  "start_time": "Tue, 23 Jan 2024 00:57:36 GMT",
  "state": "FINISHED",
  "status_code": 200,
  "tests_failed": 5,
  "tests_passed": 7,
  "tests_quantity": 12
}