{
  "algorithm_version": 3,
  "end_time": "Thu, 20 Jun 2024 00:11:57 GMT",
  "grade": "D+",
  "hidden": false,
  "likelihood_indicator": "MEDIUM",
  "response_headers": {
    "CF-Cache-Status": "DYNAMIC",
    "CF-RAY": "89678b2e583927ea-SEA",
    "Cache-Control": "no-store, no-cache, must-revalidate, post-check=0, pre-check=0",
    "Connection": "keep-alive",
    "Content-Encoding": "gzip",
    "Content-Type": "text/html; charset=ISO-8859-1",
    "Date": "Thu, 20 Jun 2024 00:11:49 GMT",
    "Expires": "Thu, 19 Nov 1981 08:52:00 GMT",
    "NEL": "{\"success_fraction\":0,\"report_to\":\"cf-nel\",\"max_age\":604800}",
    "Pragma": "no-cache",
    "Report-To": "{\"endpoints\":[{\"url\":\"https:\\/\\/a.nel.cloudflare.com\\/report\\/v4?s=%2BS7RkAoHafJKyVBA60xR%2B%2BM2gF5eJXcktVl%2FtUeQ1htOMDVUhfZNGpZj5IV0y6q9unk3fdu8y1wYvuW9rv6mYwmTEsXpXCdOSV%2Frhiz4oUsnwr0ZfauES%2FpuTa%2BW2jy9IU0wKQRg3h1G9zkq\"}],\"group\":\"cf-nel\",\"max_age\":604800}",
    "Server": "cloudflare",
    "Set-Cookie": "speise=ohkmg30iporji9rnpf757udu51; path=/; domain=.emprenemjunts.es; secure; HttpOnly",
    "Transfer-Encoding": "chunked",
    "Vary": "Accept-Encoding",
    "X-Frame-Options": "DENY",
    "alt-svc": "h3=\":443\"; ma=86400"
  },
  "scan_id": 52473647,
  "score": 40,
  "start_time": "Thu, 20 Jun 2024 00:11:48 GMT",
  "state": "FINISHED",
  "status_code": 200,
  "tests_failed": 5,
  "tests_passed": 6,
  "tests_quantity": 11
}