{
  "algorithm_version": 2,
  "end_time": "Fri, 10 Mar 2023 01:09:48 GMT",
  "grade": "F",
  "hidden": false,
  "likelihood_indicator": "MEDIUM",
  "response_headers": {
    "CF-Cache-Status": "DYNAMIC",
    "CF-RAY": "7a57ac120a44fb48-SJC",
    "Cache-Control": "no-store, no-cache, must-revalidate, post-check=0, pre-check=0",
    "Connection": "keep-alive",
    "Content-Encoding": "gzip",
    "Content-Type": "text/html; charset=ISO-8859-1",
    "Date": "Fri, 10 Mar 2023 01:09:26 GMT",
    "Expires": "Thu, 19 Nov 1981 08:52:00 GMT",
    "NEL": "{\"success_fraction\":0,\"report_to\":\"cf-nel\",\"max_age\":604800}",
    "Pragma": "no-cache",
    "Report-To": "{\"endpoints\":[{\"url\":\"https:\\/\\/a.nel.cloudflare.com\\/report\\/v3?s=Ft1FWSyM9KaWrjSRiXbdRZBFiRURAZ%2Bgw6n4Se%2FOpKPszMxtbWz%2B74XDFE53Z7q3xBd%2BgMz8p2WcFazeYIk8rtav99XKKCL7QN5EItzp%2BoK6%2Fzi8jISvLuWSywk7ppI%2BNwp%2Btsxr4P75S6fsegkrKiHN8UnBjWGT\"}],\"group\":\"cf-nel\",\"max_age\":604800}",
    "Server": "cloudflare",
    "Set-Cookie": "speise=ab4knfrsga202enf4b1ri9bi50; path=/; domain=.emprenemjunts.es",
    "Transfer-Encoding": "chunked",
    "Vary": "Accept-Encoding",
    "X-Frame-Options": "DENY",
    "alt-svc": "h3=\":443\"; ma=86400, h3-29=\":443\"; ma=86400"
  },
  "scan_id": 35123225,
  "score": 5,
  "start_time": "Fri, 10 Mar 2023 01:09:23 GMT",
  "state": "FINISHED",
  "status_code": 200,
  "tests_failed": 7,
  "tests_passed": 5,
  "tests_quantity": 12
}