{
  "algorithm_version": 2,
  "end_time": "Tue, 30 May 2023 01:04:10 GMT",
  "grade": "D+",
  "hidden": false,
  "likelihood_indicator": "MEDIUM",
  "response_headers": {
    "Accept-Ranges": "bytes",
    "Cache-Control": "max-age=0, public",
    "Connection": "keep-alive",
    "Content-Encoding": "gzip",
    "Content-Length": "13488",
    "Content-Type": "text/html; charset=UTF-8",
    "Date": "Tue, 30 May 2023 01:04:01 GMT",
    "ETag": "\"34b0-5fcde8e170550\"",
    "Expires": "Tue, 30 May 2023 01:04:01 GMT",
    "Last-Modified": "Tue, 30 May 2023 00:48:00 GMT",
    "Pragma": "public",
    "Server": "nginx",
    "Strict-Transport-Security": "max-age=31536000",
    "Vary": "Accept-Encoding,Cookie",
    "X-Content-Type-Options": "nosniff",
    "X-Frame-Options": "SAMEORIGIN",
    "X-Powered-By": "PleskLin",
    "X-XSS-Protection": "1; mode=block"
  },
  "scan_id": 37990414,
  "score": 40,
  "start_time": "Tue, 30 May 2023 01:03:46 GMT",
  "state": "FINISHED",
  "status_code": 200,
  "tests_failed": 3,
  "tests_passed": 9,
  "tests_quantity": 12
}