{
  "algorithm_version": 2,
  "end_time": "Thu, 05 Oct 2023 00:16:43 GMT",
  "grade": "F",
  "hidden": false,
  "likelihood_indicator": "MEDIUM",
  "response_headers": {
    "Cache-Control": "private, no-cache, no-store, must-revalidate",
    "Connection": "Keep-Alive",
    "Content-Length": "54326",
    "Content-Type": "text/html; charset=UTF-8",
    "Date": "Thu, 05 Oct 2023 00:16:40 GMT",
    "ETag": "\"44c5d52e\"",
    "Expires": "Thu, 01 Jan 1970 00:00:00 GMT",
    "Keep-Alive": "timeout=5, max=99",
    "Liferay-Portal": "Liferay Digital Experience Platform",
    "Pragma": "no-cache",
    "Server": "Apache",
    "Set-Cookie": "JSESSIONID=4-r9MZaYZ58MxmNdGV43BjWRmoOy2ixhu-N846-FKDUTndgMN9PN!581729396; path=/; HttpOnly, QueueITAccepted-SDFrts345E-V3_lmsr=EventId%3Dlmsr%26QueueId%3D2503d01f-77ac-445a-9654-4e61b309c398%26RedirectType%3Dsafetynet%26IssueTime%3D1696465000%26Hash%3D89ca9ebf7d90b93e67116b883d23fc3bb886abf37ab3d0643f591334c47b1697; expires=Fri, 06-Oct-2023 00:16:40 GMT; path=/; HttpOnly, COOKIE_SUPPORT=true; expires=Fri, 04-Oct-2024 00:16:40 GMT; path=/; secure; HttpOnly, GUEST_LANGUAGE_ID=ca_ES; domain=.gencat.cat; expires=Fri, 04-Oct-2024 00:16:40 GMT; path=/; secure; HttpOnly, COOKIE_SUPPORT=true; expires=Fri, 04-Oct-2024 00:16:40 GMT; path=/; secure; HttpOnly, QueueITAccepted-SDFrts345E-V3_lmsr=EventId%3Dlmsr%26QueueId%3D2503d01f-77ac-445a-9654-4e61b309c398%26RedirectType%3Dsafetynet%26IssueTime%3D1696465000%26Hash%3D89ca9ebf7d90b93e67116b883d23fc3bb886abf37ab3d0643f591334c47b1697; expires=Fri, 06-Oct-2023 00:16:40 GMT; path=/; HttpOnly, GUEST_LANGUAGE_ID=ca_ES; domain=.gencat.cat; expires=Fri, 04-Oct-2024 00:16:40 GMT; path=/; secure; HttpOnly",
    "X-Content-Type-Options": "nosniff",
    "X-Frame-Options": "SAMEORIGIN",
    "X-XSS-Protection": "1"
  },
  "scan_id": 42895607,
  "score": 15,
  "start_time": "Thu, 05 Oct 2023 00:11:00 GMT",
  "state": "FINISHED",
  "status_code": 200,
  "tests_failed": 3,
  "tests_passed": 9,
  "tests_quantity": 12
}