{
  "algorithm_version": 2,
  "end_time": "Tue, 14 Nov 2023 00:11:04 GMT",
  "grade": "F",
  "hidden": false,
  "likelihood_indicator": "MEDIUM",
  "response_headers": {
    "Cache-Control": "private, no-cache, no-store, must-revalidate",
    "Connection": "Keep-Alive",
    "Content-Length": "54326",
    "Content-Type": "text/html; charset=UTF-8",
    "Date": "Tue, 14 Nov 2023 00:11:00 GMT",
    "ETag": "\"7c8fdf8c\"",
    "Expires": "Thu, 01 Jan 1970 00:00:00 GMT",
    "Keep-Alive": "timeout=5, max=99",
    "Liferay-Portal": "Liferay Digital Experience Platform",
    "Pragma": "no-cache",
    "Server": "Apache",
    "Set-Cookie": "JSESSIONID=q7rLKsZLA8e4KR9Ctafjf-tzhW2kwN2qn0-ZsjuDi1Hc4AHJouQm!-20735819; path=/; HttpOnly, QueueITAccepted-SDFrts345E-V3_lmsr=EventId%3Dlmsr%26QueueId%3D227109d1-7c14-4d32-834d-b5819924895e%26RedirectType%3Dsafetynet%26IssueTime%3D1699920660%26Hash%3D4eaeb6c56f3e763a2d8501bf9c0c07141b632be57bb016abbe68c071deffec90; expires=Wed, 15-Nov-2023 00:11:00 GMT; path=/; HttpOnly, COOKIE_SUPPORT=true; expires=Wed, 13-Nov-2024 00:11:00 GMT; path=/; secure; HttpOnly, GUEST_LANGUAGE_ID=ca_ES; domain=.gencat.cat; expires=Wed, 13-Nov-2024 00:11:00 GMT; path=/; secure; HttpOnly, QueueITAccepted-SDFrts345E-V3_lmsr=EventId%3Dlmsr%26QueueId%3D227109d1-7c14-4d32-834d-b5819924895e%26RedirectType%3Dsafetynet%26IssueTime%3D1699920660%26Hash%3D4eaeb6c56f3e763a2d8501bf9c0c07141b632be57bb016abbe68c071deffec90; expires=Wed, 15-Nov-2023 00:11:00 GMT; path=/; HttpOnly, COOKIE_SUPPORT=true; expires=Wed, 13-Nov-2024 00:11:00 GMT; path=/; secure; HttpOnly, GUEST_LANGUAGE_ID=ca_ES; domain=.gencat.cat; expires=Wed, 13-Nov-2024 00:11:00 GMT; path=/; secure; HttpOnly",
    "X-Content-Type-Options": "nosniff",
    "X-Frame-Options": "SAMEORIGIN",
    "X-XSS-Protection": "1"
  },
  "scan_id": 44387771,
  "score": 15,
  "start_time": "Tue, 14 Nov 2023 00:10:53 GMT",
  "state": "FINISHED",
  "status_code": 200,
  "tests_failed": 3,
  "tests_passed": 9,
  "tests_quantity": 12
}