{
  "algorithm_version": 2,
  "end_time": "Thu, 21 Sep 2023 00:10:24 GMT",
  "grade": "F",
  "hidden": false,
  "likelihood_indicator": "MEDIUM",
  "response_headers": {
    "Cache-Control": "private, no-cache, no-store, must-revalidate",
    "Connection": "Keep-Alive",
    "Content-Length": "54326",
    "Content-Type": "text/html; charset=UTF-8",
    "Date": "Thu, 21 Sep 2023 00:10:20 GMT",
    "ETag": "\"174adf62\"",
    "Expires": "Thu, 01 Jan 1970 00:00:00 GMT",
    "Keep-Alive": "timeout=5, max=99",
    "Liferay-Portal": "Liferay Digital Experience Platform",
    "Pragma": "no-cache",
    "Server": "Apache",
    "Set-Cookie": "JSESSIONID=HyW1EsXEylGlpAkmqpKeilxYjliH2guSyHZGxtM-3VhDiXWbGsHT!-686684224; path=/; HttpOnly, QueueITAccepted-SDFrts345E-V3_lmsr=EventId%3Dlmsr%26QueueId%3D4a4bd7e5-7289-4f6b-a8b9-ae748d6a74a5%26RedirectType%3Dsafetynet%26IssueTime%3D1695255020%26Hash%3D68d9daa1f259849793a5d52c0845c1579bfc372c04dd0ce5465775a4c391b5dd; expires=Fri, 22-Sep-2023 00:10:21 GMT; path=/; HttpOnly, COOKIE_SUPPORT=true; expires=Fri, 20-Sep-2024 00:10:21 GMT; path=/; secure; HttpOnly, GUEST_LANGUAGE_ID=ca_ES; domain=.gencat.cat; expires=Fri, 20-Sep-2024 00:10:21 GMT; path=/; secure; HttpOnly, QueueITAccepted-SDFrts345E-V3_lmsr=EventId%3Dlmsr%26QueueId%3D4a4bd7e5-7289-4f6b-a8b9-ae748d6a74a5%26RedirectType%3Dsafetynet%26IssueTime%3D1695255020%26Hash%3D68d9daa1f259849793a5d52c0845c1579bfc372c04dd0ce5465775a4c391b5dd; expires=Fri, 22-Sep-2023 00:10:21 GMT; path=/; HttpOnly, COOKIE_SUPPORT=true; expires=Fri, 20-Sep-2024 00:10:21 GMT; path=/; secure; HttpOnly, GUEST_LANGUAGE_ID=ca_ES; domain=.gencat.cat; expires=Fri, 20-Sep-2024 00:10:21 GMT; path=/; secure; HttpOnly",
    "X-Content-Type-Options": "nosniff",
    "X-Frame-Options": "SAMEORIGIN",
    "X-XSS-Protection": "1"
  },
  "scan_id": 42386952,
  "score": 15,
  "start_time": "Thu, 21 Sep 2023 00:10:15 GMT",
  "state": "FINISHED",
  "status_code": 200,
  "tests_failed": 3,
  "tests_passed": 9,
  "tests_quantity": 12
}