{
  "algorithm_version": 2,
  "end_time": "Tue, 25 Jul 2023 00:12:47 GMT",
  "grade": "F",
  "hidden": false,
  "likelihood_indicator": "MEDIUM",
  "response_headers": {
    "Cache-Control": "private, no-cache, no-store, must-revalidate",
    "Connection": "Keep-Alive",
    "Content-Length": "54332",
    "Content-Type": "text/html; charset=UTF-8",
    "Date": "Tue, 25 Jul 2023 00:12:44 GMT",
    "ETag": "\"3eb4d6d6\"",
    "Expires": "Thu, 01 Jan 1970 00:00:00 GMT",
    "Keep-Alive": "timeout=5, max=99",
    "Liferay-Portal": "Liferay Digital Experience Platform",
    "Pragma": "no-cache",
    "Server": "Apache",
    "Set-Cookie": "JSESSIONID=wImKZB4JDX6IGsQif4qXnItIhd1r8Yzb-j22LV7Sp5HbpA2oCI7T!-121542860; path=/; HttpOnly, QueueITAccepted-SDFrts345E-V3_lmsr=EventId%3Dlmsr%26QueueId%3D6f8dbd64-cac7-4346-984a-9f5e039cdbf8%26RedirectType%3Dsafetynet%26IssueTime%3D1690243964%26Hash%3D89e833ce9073c88a0d55af22572652ae6be1a1d44ea6e4ba4d26ab97b90b013d; expires=Wed, 26-Jul-2023 00:12:44 GMT; path=/; HttpOnly, COOKIE_SUPPORT=true; expires=Wed, 24-Jul-2024 00:12:44 GMT; path=/; secure; HttpOnly, GUEST_LANGUAGE_ID=ca_ES; domain=.gencat.cat; expires=Wed, 24-Jul-2024 00:12:44 GMT; path=/; secure; HttpOnly, QueueITAccepted-SDFrts345E-V3_lmsr=EventId%3Dlmsr%26QueueId%3D6f8dbd64-cac7-4346-984a-9f5e039cdbf8%26RedirectType%3Dsafetynet%26IssueTime%3D1690243964%26Hash%3D89e833ce9073c88a0d55af22572652ae6be1a1d44ea6e4ba4d26ab97b90b013d; expires=Wed, 26-Jul-2023 00:12:44 GMT; path=/; HttpOnly, COOKIE_SUPPORT=true; expires=Wed, 24-Jul-2024 00:12:44 GMT; path=/; secure; HttpOnly, GUEST_LANGUAGE_ID=ca_ES; domain=.gencat.cat; expires=Wed, 24-Jul-2024 00:12:44 GMT; path=/; secure; HttpOnly",
    "X-Content-Type-Options": "nosniff",
    "X-Frame-Options": "SAMEORIGIN",
    "X-XSS-Protection": "1"
  },
  "scan_id": 40079645,
  "score": 15,
  "start_time": "Tue, 25 Jul 2023 00:12:38 GMT",
  "state": "FINISHED",
  "status_code": 200,
  "tests_failed": 3,
  "tests_passed": 9,
  "tests_quantity": 12
}