{
  "algorithm_version": 2,
  "end_time": "Thu, 28 Oct 2021 00:15:08 GMT",
  "grade": "F",
  "hidden": false,
  "likelihood_indicator": "MEDIUM",
  "response_headers": {
    "Accept-Ranges": "bytes",
    "Access-Control-Allow-Origin": "*",
    "Cache-Control": "public, max-age=91",
    "Connection": "keep-alive",
    "Content-Encoding": "gzip",
    "Content-Length": "31624",
    "Content-Type": "text/html;charset=UTF-8",
    "Date": "Thu, 28 Oct 2021 00:14:58 GMT",
    "Expires": "Thu, 28 Oct 2021 00:16:29 GMT",
    "Last-Modified": "Thu, 28 Oct 2021 00:11:22 GMT",
    "Server": "Apache",
    "Server-Timing": "cdn-cache; desc=REVALIDATE, edge; dur=1, origin; dur=72",
    "Vary": "Accept-Encoding",
    "X-Akamai-Transformed": "9 43451 0 pmb=mRUM,1",
    "X-Frame-Options": "SAMEORIGIN",
    "X-WA-Info": "[V2.S11101.A18718.P75851.N48551.RN0.U1522063040].[OT/html.OG/pages]"
  },
  "scan_id": 22321721,
  "score": 0,
  "start_time": "Thu, 28 Oct 2021 00:14:55 GMT",
  "state": "FINISHED",
  "status_code": 200,
  "tests_failed": 7,
  "tests_passed": 5,
  "tests_quantity": 12
}