{
  "algorithm_version": 2,
  "end_time": "Tue, 31 Jan 2023 01:06:59 GMT",
  "grade": "F",
  "hidden": false,
  "likelihood_indicator": "MEDIUM",
  "response_headers": {
    "Access-Control-Allow-Origin": "*",
    "Cache-Control": "public, max-age=3534",
    "Connection": "keep-alive",
    "Content-Encoding": "gzip",
    "Content-Length": "22959",
    "Content-Type": "text/html;charset=UTF-8",
    "Date": "Tue, 31 Jan 2023 01:06:24 GMT",
    "Expires": "Tue, 31 Jan 2023 02:05:18 GMT",
    "Last-Modified": "Tue, 31 Jan 2023 01:05:08 GMT",
    "Server": "Apache",
    "Server-Timing": "cdn-cache; desc=MISS, edge; dur=85, origin; dur=703",
    "Vary": "Accept-Encoding",
    "X-Akamai-Transformed": "9 32137 0 pmb=mRUM,1",
    "X-Frame-Options": "SAMEORIGIN"
  },
  "scan_id": 33634808,
  "score": 0,
  "start_time": "Tue, 31 Jan 2023 01:06:20 GMT",
  "state": "FINISHED",
  "status_code": 200,
  "tests_failed": 5,
  "tests_passed": 7,
  "tests_quantity": 12
}