{
  "algorithm_version": 2,
  "end_time": "Sun, 19 Jun 2022 00:59:02 GMT",
  "grade": "F",
  "hidden": false,
  "likelihood_indicator": "MEDIUM",
  "response_headers": {
    "Access-Control-Allow-Headers": "origin, x-requested-with, content-type",
    "Access-Control-Allow-Methods": "PUT, GET, POST, DELETE, OPTIONS",
    "Cache-Control": "no-store",
    "Connection": "Keep-Alive",
    "Content-Encoding": "gzip",
    "Content-Type": "text/html; charset=UTF-8",
    "Date": "Sun, 19 Jun 2022 00:58:11 GMT",
    "Keep-Alive": "timeout=5, max=99",
    "Last-Modified": "Sun, 19 Jun 2022 00:58:11 GMT",
    "Server": "ZENEDGE",
    "Service-Worker-Allowed": "/",
    "Set-Cookie": "SITESJSESSIONID=xPN5d54pNeQ2393kP5wG_7CDnbsNVMyu-W75JfYi_rTCJsqQYHKz!1146923954; path=/; HttpOnly, idioma=gl; expires=Wed, 16-Jun-2032 00:58:11 GMT; path=/, argIdioma=gl; expires=Wed, 16-Jun-2032 00:58:11 GMT; path=/, X-Oracle-BMC-LBS-Route=0753429ffaf331643dd7533496dcbd9719f6f935c061529bd171d270a1717d8e13bd978f1e8d7626; path=/; HttpOnly, X-Oracle-BMC-LBS-Route=0753429ffaf331643dd7533496dcbd9719f6f935997bf4484161f9cf08fefda6f758c2a4e58ab304; expires=Wed, 16-Jun-2032 00:58:11 GMT; path=/, X-Oracle-BMC-LBS-Route=0753429ffaf331643dd7533496dcbd9719f6f935997bf4484161f9cf08fefda6f758c2a4e58ab304; expires=Wed, 16-Jun-2032 00:58:11 GMT; path=/",
    "Transfer-Encoding": "chunked",
    "Vary": "Accept-Encoding,User-Agent",
    "Via": "1.1 sede.coruna.gal (Apache/2.4.53)",
    "X-Cache-Status": "NOTCACHED",
    "X-Cdn": "Served-By-Zenedge",
    "X-Content-Type-Options": "nosniff",
    "X-ORACLE-DMS-ECID": "3242a297-8020-4a19-846d-238db0b50def-0050d7c1",
    "X-ORACLE-DMS-RID": "0",
    "X-XSS-Protection": "1",
    "X-Zen-Fury": "c9c222222c660f4e7fa44cd91e0b12d215cd5a11",
    "device_type": "Desktop",
    "host_service": "FutureTenseContentServer:12c"
  },
  "scan_id": 27240504,
  "score": 0,
  "start_time": "Sun, 19 Jun 2022 00:57:22 GMT",
  "state": "FINISHED",
  "status_code": 200,
  "tests_failed": 5,
  "tests_passed": 7,
  "tests_quantity": 12
}