{
  "algorithm_version": 2,
  "end_time": "Fri, 27 Oct 2023 00:11:44 GMT",
  "grade": "F",
  "hidden": false,
  "likelihood_indicator": "MEDIUM",
  "response_headers": {
    "Access-Control-Allow-Headers": "origin, x-requested-with, content-type",
    "Access-Control-Allow-Methods": "PUT, GET, POST, DELETE, OPTIONS",
    "Cache-Control": "no-store",
    "Connection": "Keep-Alive",
    "Content-Encoding": "gzip",
    "Content-Length": "17200",
    "Content-Type": "text/html; charset=UTF-8",
    "Date": "Fri, 27 Oct 2023 00:11:31 GMT",
    "Keep-Alive": "timeout=5, max=99",
    "Last-Modified": "Fri, 27 Oct 2023 00:11:31 GMT",
    "Server": "ZENEDGE",
    "Service-Worker-Allowed": "/",
    "Set-Cookie": "SITESJSESSIONID=g_tueMimLnmZmeNKJgbaBzraQiByB8YKEiupr3S2ZTnPIcOah8Qs!249561855; path=/; HttpOnly, idioma=gl; expires=Mon, 24-Oct-2033 00:11:31 GMT; path=/, argIdioma=gl; expires=Mon, 24-Oct-2033 00:11:31 GMT; path=/, X-Oracle-BMC-LBS-Route=0753429ffaf331643dd7533496dcbd9719f6f935dd87d94ec98d09fd3a4e13dae05d2aae2a93a982; path=/; HttpOnly, X-Oracle-BMC-LBS-Route=0753429ffaf331643dd7533496dcbd9719f6f935997bf4484161f9cf08fefda6f758c2a4e58ab304; expires=Mon, 24-Oct-2033 00:11:31 GMT; path=/, X-Oracle-BMC-LBS-Route=0753429ffaf331643dd7533496dcbd9719f6f935997bf4484161f9cf08fefda6f758c2a4e58ab304; expires=Mon, 24-Oct-2033 00:11:31 GMT; path=/",
    "Vary": "Accept-Encoding,User-Agent",
    "Via": "1.1 sede.coruna.gal (Apache/2.4.57)",
    "X-Cache-Status": "NOTCACHED",
    "X-Cdn": "Served-By-Zenedge",
    "X-Content-Type-Options": "nosniff",
    "X-ORACLE-DMS-ECID": "d43da4da-9996-4faa-8902-9bef06be9c2f-012aa1e6",
    "X-ORACLE-DMS-RID": "0",
    "X-XSS-Protection": "1",
    "X-Zen-Fury": "62296775a65c21639a9d97a761c061432d200ba6",
    "device_type": "Desktop",
    "host_service": "FutureTenseContentServer:12c"
  },
  "scan_id": 43697716,
  "score": 0,
  "start_time": "Fri, 27 Oct 2023 00:10:36 GMT",
  "state": "FINISHED",
  "status_code": 200,
  "tests_failed": 5,
  "tests_passed": 7,
  "tests_quantity": 12
}