{
  "algorithm_version": 2,
  "end_time": "Sun, 29 Oct 2023 00:55:32 GMT",
  "grade": "F",
  "hidden": false,
  "likelihood_indicator": "MEDIUM",
  "response_headers": {
    "Access-Control-Allow-Headers": "origin, x-requested-with, content-type",
    "Access-Control-Allow-Methods": "PUT, GET, POST, DELETE, OPTIONS",
    "Cache-Control": "no-store",
    "Connection": "Keep-Alive",
    "Content-Encoding": "gzip",
    "Content-Length": "17207",
    "Content-Type": "text/html; charset=UTF-8",
    "Date": "Sun, 29 Oct 2023 00:55:23 GMT",
    "Keep-Alive": "timeout=5, max=99",
    "Last-Modified": "Sun, 29 Oct 2023 00:55:23 GMT",
    "Server": "ZENEDGE",
    "Service-Worker-Allowed": "/",
    "Set-Cookie": "SITESJSESSIONID=uil47aj07npiKqEqbH1VqIOTDQt2RtJ0piy2IxTUcKydp_QxLhHf!249561855; path=/; HttpOnly, idioma=gl; expires=Wed, 26-Oct-2033 00:55:23 GMT; path=/, argIdioma=gl; expires=Wed, 26-Oct-2033 00:55:23 GMT; path=/, X-Oracle-BMC-LBS-Route=0753429ffaf331643dd7533496dcbd9719f6f935644aec68cfcf386fedce29bc0bae120d21e33a0f; path=/; HttpOnly, X-Oracle-BMC-LBS-Route=0753429ffaf331643dd7533496dcbd9719f6f935997bf4484161f9cf08fefda6f758c2a4e58ab304; expires=Wed, 26-Oct-2033 00:55:23 GMT; path=/, X-Oracle-BMC-LBS-Route=0753429ffaf331643dd7533496dcbd9719f6f935997bf4484161f9cf08fefda6f758c2a4e58ab304; expires=Wed, 26-Oct-2033 00:55:23 GMT; path=/",
    "Vary": "Accept-Encoding,User-Agent",
    "Via": "1.1 sede.coruna.gal (Apache/2.4.57)",
    "X-Cache-Status": "NOTCACHED",
    "X-Cdn": "Served-By-Zenedge",
    "X-Content-Type-Options": "nosniff",
    "X-ORACLE-DMS-ECID": "d43da4da-9996-4faa-8902-9bef06be9c2f-0137fff0",
    "X-ORACLE-DMS-RID": "0",
    "X-XSS-Protection": "1",
    "X-Zen-Fury": "6eaa6b7433094fc555c52c16a792e9fd4b9f4881",
    "device_type": "Desktop",
    "host_service": "FutureTenseContentServer:12c"
  },
  "scan_id": 43754809,
  "score": 0,
  "start_time": "Sun, 29 Oct 2023 00:55:15 GMT",
  "state": "FINISHED",
  "status_code": 200,
  "tests_failed": 5,
  "tests_passed": 7,
  "tests_quantity": 12
}