{
  "algorithm_version": 2,
  "end_time": "Tue, 17 May 2022 00:12:59 GMT",
  "grade": "F",
  "hidden": false,
  "likelihood_indicator": "MEDIUM",
  "response_headers": {
    "CF-Cache-Status": "DYNAMIC",
    "CF-RAY": "70c8245dea5424fa-SJC",
    "Connection": "keep-alive",
    "Content-Encoding": "gzip",
    "Content-Type": "text/html; charset=UTF-8",
    "Date": "Tue, 17 May 2022 00:12:34 GMT",
    "Expect-CT": "max-age=604800, report-uri=\"https://report-uri.cloudflare.com/cdn-cgi/beacon/expect-ct\"",
    "NEL": "{\"success_fraction\":0,\"report_to\":\"cf-nel\",\"max_age\":604800}",
    "Report-To": "{\"endpoints\":[{\"url\":\"https:\\/\\/a.nel.cloudflare.com\\/report\\/v3?s=rePpcq%2FDZ1efkv3NQRXOR5HkgaidCQcqx%2Fk2ioU3Mm0dsFynzq40M7Bc%2F5ZkoZOrv44Cz1msTaGfqV81trNREU8Du4wvfObklsh%2BMtfgwyhF3QD54syAVdjPASp76KB%2FNX41C%2B2DakGOdYAdIKRJ3%2F3VuZ52nxu8G9E%3D\"}],\"group\":\"cf-nel\",\"max_age\":604800}",
    "Server": "cloudflare",
    "Transfer-Encoding": "chunked",
    "alt-svc": "h3=\":443\"; ma=86400, h3-29=\":443\"; ma=86400",
    "link": "<https://www.vegadelguadalquivir.org/wp-json/>; rel=\"https://api.w.org/\", <https://www.vegadelguadalquivir.org/>; rel=shortlink",
    "strict-transport-security": "max-age=15768000; includeSubDomains",
    "vary": "Accept-Encoding",
    "x-powered-by": "PHP/7.4.28, PleskLin"
  },
  "scan_id": 26487556,
  "score": 20,
  "start_time": "Tue, 17 May 2022 00:12:27 GMT",
  "state": "FINISHED",
  "status_code": 200,
  "tests_failed": 5,
  "tests_passed": 7,
  "tests_quantity": 12
}