{
  "algorithm_version": 3,
  "end_time": "Sun, 30 Jun 2024 00:14:16 GMT",
  "grade": "F",
  "hidden": false,
  "likelihood_indicator": "MEDIUM",
  "response_headers": {
    "Cache-Control": "private, no-cache, no-store, must-revalidate",
    "Connection": "Keep-Alive",
    "Content-Type": "text/html;charset=UTF-8",
    "Date": "Sun, 30 Jun 2024 00:14:12 GMT",
    "Expires": "Thu, 01 Jan 1970 00:00:00 GMT",
    "Keep-Alive": "timeout=15, max=100",
    "Liferay-Portal": "Liferay Digital Experience Platform",
    "Pragma": "no-cache",
    "Server": "Apache",
    "Set-Cookie": "JSESSIONID=4CFB4DE346A4BCFD55F01AA4C7D0EE3E.srt2; Path=/; Secure; HttpOnly, COOKIE_SUPPORT=true; Max-Age=31536000; Expires=Mon, 30-Jun-2025 00:14:10 GMT; Path=/; Secure; HttpOnly, GUEST_LANGUAGE_ID=es_ES; Max-Age=31536000; Expires=Mon, 30-Jun-2025 00:14:10 GMT; Path=/; Secure; HttpOnly, cookiesession1=678B2A520625939D44C7B09DC9E80F82;Expires=Mon, 30 Jun 2025 00:14:12 GMT;Path=/;HttpOnly",
    "X-Content-Type-Options": "nosniff",
    "X-Frame-Options": "SAMEORIGIN",
    "X-XSS-Protection": "1",
    "content-length": "108277"
  },
  "scan_id": 52856634,
  "score": 10,
  "start_time": "Sun, 30 Jun 2024 00:14:06 GMT",
  "state": "FINISHED",
  "status_code": 200,
  "tests_failed": 4,
  "tests_passed": 7,
  "tests_quantity": 11
}