{
  "algorithm_version": 2,
  "end_time": "Mon, 06 Mar 2023 00:12:34 GMT",
  "grade": "B",
  "hidden": false,
  "likelihood_indicator": "MEDIUM",
  "response_headers": {
    "CF-Cache-Status": "DYNAMIC",
    "CF-RAY": "7a3662e58a9596f0-SJC",
    "Cache-Control": "no-cache",
    "Connection": "keep-alive",
    "Content-Encoding": "gzip",
    "Content-Type": "text/html; charset=UTF-8",
    "Date": "Mon, 06 Mar 2023 00:12:18 GMT",
    "Last-Modified": "Fri, 03 Mar 2023 18:54:10 GMT",
    "NEL": "{\"success_fraction\":0,\"report_to\":\"cf-nel\",\"max_age\":604800}",
    "Referrer-Policy": "strict-origin",
    "Report-To": "{\"endpoints\":[{\"url\":\"https:\\/\\/a.nel.cloudflare.com\\/report\\/v3?s=RAyRkXu4Gms0UFuI2swvHzlP8CqMfujdGktcNZf0zbhm4pZkqVOIvVsdjmamVhnRdxQ3zZJ7O5lkqs0Qb%2Fg%2Bdn6jm7oR0sCaBqULI1xrkJrrJuf6XpOKqqI88vKPha1J3zKRfuQjHMpMirUBvhKRGRU%2FOCAf6%2FSc8xwM\"}],\"group\":\"cf-nel\",\"max_age\":604800}",
    "Server": "cloudflare",
    "Server-Timing": "cf-q-config;dur=6.9999950937927e-06",
    "Strict-Transport-Security": "max-age=31536000; includeSubDomains; preload",
    "Transfer-Encoding": "chunked",
    "Vary": "User-Agent",
    "WPO-Cache-Status": "cached",
    "X-Content-Type-Options": "nosniff",
    "X-Frame-Options": "sameorigin",
    "X-XSS-Protection": "1;  mode=block",
    "alt-svc": "h3=\":443\"; ma=86400, h3-29=\":443\"; ma=86400"
  },
  "scan_id": 34964284,
  "score": 70,
  "start_time": "Mon, 06 Mar 2023 00:12:16 GMT",
  "state": "FINISHED",
  "status_code": 200,
  "tests_failed": 2,
  "tests_passed": 10,
  "tests_quantity": 12
}