{
  "algorithm_version": 2,
  "end_time": "Wed, 07 Jun 2023 00:12:26 GMT",
  "grade": "F",
  "hidden": false,
  "likelihood_indicator": "MEDIUM",
  "response_headers": {
    "CF-Cache-Status": "DYNAMIC",
    "CF-RAY": "7d34aea9b906fa7e-SJC",
    "Cache-Control": "max-age=3, must-revalidate, max-age=2592000",
    "Connection": "keep-alive",
    "Content-Encoding": "gzip",
    "Content-Type": "text/html; charset=UTF-8",
    "Date": "Wed, 07 Jun 2023 00:12:14 GMT",
    "NEL": "{\"success_fraction\":0,\"report_to\":\"cf-nel\",\"max_age\":604800}",
    "Report-To": "{\"endpoints\":[{\"url\":\"https:\\/\\/a.nel.cloudflare.com\\/report\\/v3?s=7Nm7L8OdK6sOm8p%2BWW89teThGn0NZenNe2KxepA5xq2LvGL%2FNbdxDlQBYzKq8aGVoX6340hHASUKT7a364tBtbqpLWGUbPq98t6Q2N54%2Fonu0rYHGn9RYCi4KVowV8lqk8F%2FJ5BY\"}],\"group\":\"cf-nel\",\"max_age\":604800}",
    "Server": "cloudflare",
    "Transfer-Encoding": "chunked",
    "alt-svc": "h3=\":443\"; ma=86400",
    "content-security-policy": "object-src 'none'",
    "expires": "Fri, 07 Jul 2023 00:12:11 GMT",
    "host-header": "8441280b0c35cbc1147f8ba998a563a7",
    "last-modified": "Wed, 07 Jun 2023 00:11:38 GMT",
    "strict-transport-security": "max-age=63072000",
    "vary": "Accept-Encoding, Accept-Encoding,Cookie",
    "x-content-type-options": "nosniff",
    "x-httpd-modphp": "1",
    "x-proxy-cache": "HIT",
    "x-xss-protection": "1; mode=block"
  },
  "scan_id": 38245475,
  "score": 0,
  "start_time": "Wed, 07 Jun 2023 00:12:09 GMT",
  "state": "FINISHED",
  "status_code": 200,
  "tests_failed": 4,
  "tests_passed": 8,
  "tests_quantity": 12
}