{
  "algorithm_version": 2,
  "end_time": "Fri, 26 Mar 2021 02:22:41 GMT",
  "grade": "F",
  "hidden": false,
  "likelihood_indicator": "MEDIUM",
  "response_headers": {
    "Connection": "keep-alive",
    "Content-Length": "146",
    "Content-Type": "text/html",
    "Date": "Fri, 26 Mar 2021 02:22:40 GMT",
    "Server": "nginx"
  },
  "scan_id": 18388656,
  "score": 0,
  "start_time": "Fri, 26 Mar 2021 02:22:38 GMT",
  "state": "FINISHED",
  "status_code": 403,
  "tests_failed": 6,
  "tests_passed": 6,
  "tests_quantity": 12
}