{
  "algorithm_version": 2,
  "end_time": "Sat, 08 Jul 2023 00:14:11 GMT",
  "grade": "F",
  "hidden": false,
  "likelihood_indicator": "MEDIUM",
  "response_headers": {
    "Access-Control-Allow-Origin": "*",
    "Cache-Control": "PUBLIC, max-age=300, must-revalidate",
    "Connection": "Keep-Alive",
    "Content-Encoding": "gzip",
    "Content-Type": "text/html;charset=ISO-8859-15",
    "Date": "Sat, 08 Jul 2023 00:14:01 GMT",
    "Expires": "Sat, 08 Jul 2023 02:14:01 CEST",
    "Keep-Alive": "timeout=5, max=100",
    "Last-Modified": "Fri, 07 Jul 2023 13:36:14 CEST",
    "Server": "Apache",
    "Set-Cookie": "IGSESSIONID=A4F5FE4DED2F50B3C8C3027DA26320AB.infogluelive1; Path=/; HttpOnly",
    "Transfer-Encoding": "chunked"
  },
  "scan_id": 39486379,
  "score": 0,
  "start_time": "Sat, 08 Jul 2023 00:08:50 GMT",
  "state": "FINISHED",
  "status_code": 200,
  "tests_failed": 9,
  "tests_passed": 3,
  "tests_quantity": 12
}