{
  "algorithm_version": 2,
  "end_time": "Sun, 29 Oct 2023 01:08:22 GMT",
  "grade": "F",
  "hidden": false,
  "likelihood_indicator": "MEDIUM",
  "response_headers": {
    "Connection": "keep-alive",
    "Content-Type": "text/html; charset=utf-8",
    "Date": "Sun, 29 Oct 2023 01:08:12 GMT",
    "Server": "Microsoft-IIS/10.0",
    "Set-Cookie": "ApplicationGatewayAffinityCORS=ddc89dc2c711b138801b0ef8db6d205f; Path=/; SameSite=None; Secure, ApplicationGatewayAffinity=ddc89dc2c711b138801b0ef8db6d205f; Path=/",
    "Transfer-Encoding": "chunked"
  },
  "scan_id": 43755064,
  "score": 0,
  "start_time": "Sun, 29 Oct 2023 01:08:03 GMT",
  "state": "FINISHED",
  "status_code": 200,
  "tests_failed": 7,
  "tests_passed": 5,
  "tests_quantity": 12
}