{
  "algorithm_version": 2,
  "end_time": "Mon, 14 Nov 2022 01:47:57 GMT",
  "grade": "F",
  "hidden": false,
  "likelihood_indicator": "MEDIUM",
  "response_headers": {
    "Accept-Ranges": "bytes",
    "Age": "107",
    "Cache-Control": "max-age=0, no-cache,must-revalidate",
    "Connection": "keep-alive",
    "Content-Length": "275288",
    "Content-Type": "text/html; charset=UTF-8",
    "Date": "Mon, 14 Nov 2022 01:47:53 GMT",
    "Last-Modified": "Mon, 14 Nov 2022 01:47:53 GMT",
    "Pragma": "public",
    "Vary": "Accept-Encoding",
    "X-Cache": "HIT, MISS",
    "X-Cache-Hits": "9, 0",
    "X-Served-By": "cache-mad22086-MAD, cache-sjc10050-SJC",
    "X-Timer": "S1668390473.437644,VS0,VE163",
    "x-esi-status": "1, 1",
    "x-gzip-status": "0, 0"
  },
  "scan_id": 30882566,
  "score": 15,
  "start_time": "Mon, 14 Nov 2022 01:46:43 GMT",
  "state": "FINISHED",
  "status_code": 200,
  "tests_failed": 6,
  "tests_passed": 6,
  "tests_quantity": 12
}