{
  "algorithm_version": 2,
  "end_time": "Tue, 22 Aug 2023 01:02:45 GMT",
  "grade": "F",
  "hidden": false,
  "likelihood_indicator": "MEDIUM",
  "response_headers": {
    "Cache-Control": "no-cache",
    "Connection": "keep-alive",
    "Content-Encoding": "gzip",
    "Content-Type": "text/html; charset=UTF-8",
    "Date": "Tue, 22 Aug 2023 01:02:40 GMT",
    "Expires": "Thu, 01 Jan 1970 00:00:01 GMT",
    "Referrer-Policy": "strict-origin-when-cross-origin",
    "Set-Cookie": "AWSALB=/k4WY0GWnMV7iavs6NsjvPjF2WS9a1pnKsrxLSQl1Ywkm9QsWV2EeZ91+/9WjTl+6t6kgoZ3AhfnWJ9DjhAXtzk3ybKBo8iUCJiesAXuKoIsLNaGitrkRlWdN0jn; Expires=Tue, 29 Aug 2023 01:02:40 GMT; Path=/, AWSALBCORS=/k4WY0GWnMV7iavs6NsjvPjF2WS9a1pnKsrxLSQl1Ywkm9QsWV2EeZ91+/9WjTl+6t6kgoZ3AhfnWJ9DjhAXtzk3ybKBo8iUCJiesAXuKoIsLNaGitrkRlWdN0jn; Expires=Tue, 29 Aug 2023 01:02:40 GMT; Path=/; SameSite=None; Secure",
    "Transfer-Encoding": "chunked",
    "Vary": "Accept-Encoding",
    "X-Content-Type-Options": "nosniff",
    "X-FastCGI-Cache": "HIT",
    "X-FastCGI-Zone": "cache_cartv_sm",
    "X-XSS-Protection": "1; mode=block"
  },
  "scan_id": 41140317,
  "score": 0,
  "start_time": "Tue, 22 Aug 2023 01:02:35 GMT",
  "state": "FINISHED",
  "status_code": 200,
  "tests_failed": 5,
  "tests_passed": 7,
  "tests_quantity": 12
}