{
  "algorithm_version": 2,
  "end_time": "Sun, 07 May 2023 01:38:22 GMT",
  "grade": "B",
  "hidden": false,
  "likelihood_indicator": "MEDIUM",
  "response_headers": {
    "Accept-Ranges": "bytes",
    "Connection": "Upgrade, Keep-Alive",
    "Content-Encoding": "gzip",
    "Content-Type": "text/html",
    "Date": "Sun, 07 May 2023 01:38:18 GMT",
    "Keep-Alive": "timeout=15, max=100",
    "Last-Modified": "Mon, 18 Apr 2022 07:48:09 GMT",
    "Referrer-Policy": "no-referrer-when-downgrade",
    "Set-Cookie": "nlbi_171420=u907IsIfbApW2+UW3tof+wAAAAC7Y3mRGj9uGArAYlrO+8ol; path=/; Domain=.grancanaria.com; Secure; SameSite=None, visid_incap_171420=Tz0wJKsoRueJ+WhMc41WNggBV2QAAAAAQUIPAAAAAABn3VUAibmSEIFd8h+lvqJz; expires=Sun, 05 May 2024 07:49:26 GMT; HttpOnly; path=/; Domain=.grancanaria.com; Secure; SameSite=None, incap_ses_1163_171420=h2dtWth733nJnbFxOM8jEAkBV2QAAAAARfe2NgIcgwnLiwTM9crafQ==; path=/; Domain=.grancanaria.com; Secure; SameSite=None",
    "Strict-Transport-Security": "max-age=31536000",
    "Transfer-Encoding": "chunked",
    "Upgrade": "h2",
    "Vary": "Accept-Encoding",
    "X-CDN": "Imperva",
    "X-Content-Type-Options": "nosniff",
    "X-Frame-Options": "SAMEORIGIN",
    "X-Iinfo": "5-27414623-27414626 nNNN RT(1683423497386 31) q(0 0 3 0) r(4 5) U12",
    "X-XSS-Protection": "1; mode=block"
  },
  "scan_id": 37099365,
  "score": 70,
  "start_time": "Sun, 07 May 2023 01:38:15 GMT",
  "state": "FINISHED",
  "status_code": 200,
  "tests_failed": 2,
  "tests_passed": 10,
  "tests_quantity": 12
}