{
  "algorithm_version": 2,
  "end_time": "Sun, 30 Jul 2023 00:08:55 GMT",
  "grade": "F",
  "hidden": false,
  "likelihood_indicator": "MEDIUM",
  "response_headers": {
    "Access-Control-Allow-Headers": "origin, x-requested-with, content-type",
    "Access-Control-Allow-Methods": "PUT, GET, POST, DELETE, OPTIONS",
    "Cache-Control": "no-store",
    "Connection": "keep-alive",
    "Content-Encoding": "gzip",
    "Content-Type": "text/html; charset=UTF-8",
    "Date": "Sun, 30 Jul 2023 00:08:34 GMT",
    "Last-Modified": "Sun, 30 Jul 2023 00:08:34 GMT",
    "Server": "ZENEDGE",
    "Service-Worker-Allowed": "/",
    "Set-Cookie": "SITESJSESSIONID=YKWkIBsM0GYEVZYNC6QhmaxgY-uxExIydYpHKOeeM365M-hfKu2i!-2066560474; path=/; HttpOnly, idioma=gl; expires=Wed, 27-Jul-2033 00:08:34 GMT; path=/, argIdioma=gl; expires=Wed, 27-Jul-2033 00:08:34 GMT; path=/, X-Oracle-BMC-LBS-Route=f0ee94706ee2ee72f2eb77e9a46b082c67a77d11c5ad4da208f36959b8f5f1ac26d7bd2c3fc47f02; path=/; HttpOnly, X-Oracle-BMC-LBS-Route=f0ee94706ee2ee72f2eb77e9a46b082c67a77d11997bf4484161f9cf08fefda6f758c2a4e58ab304; expires=Wed, 27-Jul-2033 00:08:34 GMT; path=/, X-Oracle-BMC-LBS-Route=f0ee94706ee2ee72f2eb77e9a46b082c67a77d11997bf4484161f9cf08fefda6f758c2a4e58ab304; expires=Wed, 27-Jul-2033 00:08:34 GMT; path=/",
    "Transfer-Encoding": "chunked",
    "Vary": "Accept-Encoding,User-Agent",
    "X-Cache-Status": "NOTCACHED",
    "X-Cdn": "Served-By-Zenedge",
    "X-Content-Type-Options": "nosniff",
    "X-ORACLE-DMS-ECID": "4a74af60-8377-4ec3-ac1a-85b2411e4587-0070f43e",
    "X-ORACLE-DMS-RID": "0",
    "X-XSS-Protection": "1",
    "X-Zen-Fury": "d359b06a88cc0507703f38498594aed8284e1116",
    "device_type": "Desktop",
    "host_service": "FutureTenseContentServer:12c"
  },
  "scan_id": 40196954,
  "score": 0,
  "start_time": "Sun, 30 Jul 2023 00:08:30 GMT",
  "state": "FINISHED",
  "status_code": 200,
  "tests_failed": 5,
  "tests_passed": 7,
  "tests_quantity": 12
}