{
  "algorithm_version": 2,
  "end_time": "Sat, 08 Oct 2022 01:26:21 GMT",
  "grade": "F",
  "hidden": false,
  "likelihood_indicator": "MEDIUM",
  "response_headers": {
    "Accept-Ranges": "bytes",
    "Cache-Control": "max-age=745",
    "Connection": "Keep-Alive",
    "Content-Encoding": "gzip",
    "Content-Length": "13150",
    "Content-Type": "text/html",
    "Date": "Sat, 08 Oct 2022 01:26:09 GMT",
    "ETag": "\"335e-5ea7b90d2b8f6\"",
    "Expires": "Sat, 08 Oct 2022 01:38:35 GMT",
    "Keep-Alive": "timeout=5, max=99",
    "Last-Modified": "Sat, 08 Oct 2022 01:08:35 GMT",
    "Server": "Apache"
  },
  "scan_id": 29966171,
  "score": 15,
  "start_time": "Sat, 08 Oct 2022 01:21:38 GMT",
  "state": "FINISHED",
  "status_code": 200,
  "tests_failed": 6,
  "tests_passed": 6,
  "tests_quantity": 12
}