{
  "algorithm_version": 2,
  "end_time": "Sun, 20 Aug 2023 00:56:13 GMT",
  "grade": "D",
  "hidden": false,
  "likelihood_indicator": "MEDIUM",
  "response_headers": {
    "cache-control": "private",
    "content-encoding": "gzip",
    "content-length": "10725",
    "content-type": "text/html;charset=utf-8",
    "date": "Sun, 20 Aug 2023 00:56:03 GMT",
    "set-cookie": "fe_typo_user=0b52848a76a445c151821f1b95f8f3ea; path=/, lb_9b758c85a72cdb131d41397a67782e28=i_7a70a0c275d54b62777951836011441d; path=/; HttpOnly",
    "strict-transport-security": "max-age=15552000",
    "vary": "Accept-Encoding,"
  },
  "scan_id": 41067725,
  "score": 30,
  "start_time": "Sun, 20 Aug 2023 00:52:05 GMT",
  "state": "FINISHED",
  "status_code": 200,
  "tests_failed": 6,
  "tests_passed": 6,
  "tests_quantity": 12
}