{
  "algorithm_version": 2,
  "end_time": "Tue, 05 Jul 2022 00:59:19 GMT",
  "grade": "F",
  "hidden": false,
  "likelihood_indicator": "MEDIUM",
  "response_headers": {
    "cache-control": "private",
    "content-encoding": "gzip",
    "content-length": "11099",
    "content-type": "text/html;charset=utf-8",
    "date": "Tue, 05 Jul 2022 00:59:11 GMT",
    "set-cookie": "fe_typo_user=e82c72bd8d585b3835ec194f105a9d82; path=/, lb_339828a4270757b362235fe0e798a01f=i_6cf9a6d3594af5205a94754b2a84ea01; path=/; HttpOnly",
    "strict-transport-security": "max-age=15552000",
    "vary": "Accept-Encoding,"
  },
  "scan_id": 27589984,
  "score": 0,
  "start_time": "Tue, 05 Jul 2022 00:59:05 GMT",
  "state": "FINISHED",
  "status_code": 200,
  "tests_failed": 7,
  "tests_passed": 5,
  "tests_quantity": 12
}