{
  "algorithm_version": 2,
  "end_time": "Wed, 20 Dec 2023 00:46:05 GMT",
  "grade": "F",
  "hidden": false,
  "likelihood_indicator": "MEDIUM",
  "response_headers": {
    "Cache-Control": "no-cache",
    "Connection": "keep-alive",
    "Content-Encoding": "gzip",
    "Content-Type": "text/html; charset=UTF-8",
    "Date": "Wed, 20 Dec 2023 00:46:01 GMT",
    "Expires": "Thu, 01 Jan 1970 00:00:01 GMT",
    "Referrer-Policy": "strict-origin-when-cross-origin",
    "Set-Cookie": "AWSALB=EM86gNjgrQPxxbuO8wolUBMF5UCU0hP6ujyoi8C1OxWtgJo6KwdlwkXl58gJxwQDC13IdYrfmalgpcd/Kv98ILiof0ih/xpGTO1QnitOY3jYlyzSQ9ODAAlGAYeG; Expires=Wed, 27 Dec 2023 00:46:01 GMT; Path=/, AWSALBCORS=EM86gNjgrQPxxbuO8wolUBMF5UCU0hP6ujyoi8C1OxWtgJo6KwdlwkXl58gJxwQDC13IdYrfmalgpcd/Kv98ILiof0ih/xpGTO1QnitOY3jYlyzSQ9ODAAlGAYeG; Expires=Wed, 27 Dec 2023 00:46:01 GMT; Path=/; SameSite=None; Secure",
    "Transfer-Encoding": "chunked",
    "Vary": "Accept-Encoding",
    "X-Content-Type-Options": "nosniff",
    "X-FastCGI-Cache": "HIT",
    "X-FastCGI-Zone": "cache_cartv_sm",
    "X-XSS-Protection": "1; mode=block"
  },
  "scan_id": 45633432,
  "score": 0,
  "start_time": "Wed, 20 Dec 2023 00:45:58 GMT",
  "state": "FINISHED",
  "status_code": 200,
  "tests_failed": 5,
  "tests_passed": 7,
  "tests_quantity": 12
}