{
  "algorithm_version": 3,
  "end_time": "Fri, 09 Feb 2024 00:52:18 GMT",
  "grade": "F",
  "hidden": false,
  "likelihood_indicator": "MEDIUM",
  "response_headers": {
    "Connection": "Keep-Alive",
    "Content-Encoding": "gzip",
    "Content-Language": "gl",
    "Content-Length": "5220",
    "Content-Type": "text/html;charset=ISO-8859-1",
    "Date": "Fri, 09 Feb 2024 00:52:14 GMT",
    "Keep-Alive": "timeout=5, max=99",
    "Server": "Apache",
    "Set-Cookie": "JSESSIONID=E5EFCCB18EB670E1E6E8CC8B5AA4843C; Path=/portal_localweb",
    "Vary": "Accept-Encoding"
  },
  "scan_id": 47341102,
  "score": 0,
  "start_time": "Fri, 09 Feb 2024 00:52:14 GMT",
  "state": "FINISHED",
  "status_code": 200,
  "tests_failed": 7,
  "tests_passed": 4,
  "tests_quantity": 11
}