{
  "algorithm_version": 2,
  "end_time": "Tue, 09 Nov 2021 00:08:19 GMT",
  "grade": "D-",
  "hidden": false,
  "likelihood_indicator": "MEDIUM",
  "response_headers": {
    "Accept-Ranges": "bytes",
    "Connection": "Upgrade, Keep-Alive",
    "Content-Encoding": "gzip",
    "Content-Type": "text/html",
    "Date": "Tue, 09 Nov 2021 00:08:07 GMT",
    "Keep-Alive": "timeout=15, max=100",
    "Last-Modified": "Tue, 23 Feb 2021 12:03:01 GMT",
    "Referrer-Policy": "no-referrer-when-downgrade",
    "Set-Cookie": "nlbi_171420=TqWYAe9o4gMKofuZ3tof+wAAAAAY79TiTTw2VNFkNxvsfyGp; path=/; Domain=.grancanaria.com; Secure; SameSite=None, visid_incap_171420=dua5bRX0SqiDPWWm2ahEuea7iWEAAAAAQUIPAAAAAABthBkJJhb8pEqFjbi8f8AY; expires=Tue, 08 Nov 2022 07:59:25 GMT; HttpOnly; path=/; Domain=.grancanaria.com; Secure; SameSite=None, incap_ses_977_171420=8GmZZ9wf0gREVmT0xACPDee7iWEAAAAAXW8iLKfAEMXnR3jmRNejdA==; path=/; Domain=.grancanaria.com; Secure; SameSite=None",
    "Strict-Transport-Security": "max-age=31536000",
    "Transfer-Encoding": "chunked",
    "Upgrade": "h2",
    "Vary": "Accept-Encoding",
    "X-CDN": "Imperva",
    "X-Content-Type-Options": "nosniff",
    "X-Frame-Options": "SAMEORIGIN",
    "X-Iinfo": "14-60128810-57264801 pNNN RT(1636416486832 57) q(0 0 0 0) r(2 2) U12",
    "X-XSS-Protection": "1; mode=block"
  },
  "scan_id": 22590225,
  "score": 25,
  "start_time": "Tue, 09 Nov 2021 00:07:54 GMT",
  "state": "FINISHED",
  "status_code": 200,
  "tests_failed": 2,
  "tests_passed": 10,
  "tests_quantity": 12
}