{
  "algorithm_version": 2,
  "end_time": "Sat, 01 Jan 2022 00:57:34 GMT",
  "grade": "F",
  "hidden": false,
  "likelihood_indicator": "MEDIUM",
  "response_headers": {
    "Accept-Ranges": "bytes",
    "Cache-Control": "max-age=234",
    "Connection": "Keep-Alive",
    "Content-Encoding": "gzip",
    "Content-Length": "12909",
    "Content-Type": "text/html",
    "Date": "Sat, 01 Jan 2022 00:57:27 GMT",
    "ETag": "\"326d-5d47a68256e35\"",
    "Expires": "Sat, 01 Jan 2022 01:01:21 GMT",
    "Keep-Alive": "timeout=5, max=99",
    "Last-Modified": "Sat, 01 Jan 2022 00:31:21 GMT",
    "Server": "Apache"
  },
  "scan_id": 23607287,
  "score": 0,
  "start_time": "Sat, 01 Jan 2022 00:57:19 GMT",
  "state": "FINISHED",
  "status_code": 200,
  "tests_failed": 6,
  "tests_passed": 6,
  "tests_quantity": 12
}