{
  "algorithm_version": 2,
  "end_time": "Tue, 12 Apr 2022 00:10:32 GMT",
  "grade": "B",
  "hidden": false,
  "likelihood_indicator": "MEDIUM",
  "response_headers": {
    "CF-Cache-Status": "DYNAMIC",
    "CF-RAY": "6fa7bd381f19969a-SJC",
    "Cache-Control": "no-cache, max-age=31536000, public",
    "Connection": "keep-alive",
    "Content-Encoding": "gzip",
    "Content-Security-Policy-Report-Only": "default-src 'none'; script-src 'self'; connect-src 'self; img-src 'self'>",
    "Content-Type": "text/html; charset=UTF-8",
    "Date": "Tue, 12 Apr 2022 00:10:28 GMT",
    "Expect-CT": "max-age=604800, report-uri=\"https://report-uri.cloudflare.com/cdn-cgi/beacon/expect-ct\"",
    "Expires": "Wed, 12 Apr 2023 00:10:28 GMT",
    "Last-Modified": "Sun, 10 Apr 2022 21:55:55 GMT",
    "NEL": "{\"success_fraction\":0,\"report_to\":\"cf-nel\",\"max_age\":604800}",
    "Referrer-Policy": "strict-origin",
    "Report-To": "{\"endpoints\":[{\"url\":\"https:\\/\\/a.nel.cloudflare.com\\/report\\/v3?s=zAaN5ROPG5t6jttSaOCKw%2F3drP5w6GrjRFR8SjBXQjYaXEIAxSjKRRPoLzZllf%2BtIvz9xoRdlpR6vSHn%2F4E5H4PkjZ41kWm5zGFFhZbAE4igyck1zIW0SCKcJlkEae5SJwrkNw%2F5UKAD5mpYk798NdV1vUpQOO7QNceM\"}],\"group\":\"cf-nel\",\"max_age\":604800}",
    "Server": "cloudflare",
    "Strict-Transport-Security": "max-age=31536000; includeSubDomains; preload",
    "Transfer-Encoding": "chunked",
    "WPO-Cache-Status": "cached",
    "X-Content-Type-Options": "nosniff",
    "X-Frame-Options": "sameorigin",
    "X-XSS-Protection": "1;  mode=block",
    "alt-svc": "h3=\":443\"; ma=86400, h3-29=\":443\"; ma=86400"
  },
  "scan_id": 25757555,
  "score": 75,
  "start_time": "Tue, 12 Apr 2022 00:10:25 GMT",
  "state": "FINISHED",
  "status_code": 200,
  "tests_failed": 1,
  "tests_passed": 11,
  "tests_quantity": 12
}