{
  "algorithm_version": 2,
  "end_time": "Sun, 08 Jan 2023 01:07:12 GMT",
  "grade": "F",
  "hidden": false,
  "likelihood_indicator": "MEDIUM",
  "response_headers": {
    "Content-Length": "43457",
    "Content-Type": "text/html",
    "Date": "Sun, 08 Jan 2023 01:07:09 GMT",
    "Feature-Policy": "microphone 'none'; usb 'none'; payment 'none'",
    "Set-Cookie": "TS011b0901=018ac16f67c90c2c7f23c902255b2bf9a8dda92fc873aac46ad0ffac03b194420a0e53ae6fae8716f6737f4ab9200cefa47e371e58; Path=/; Domain=.www.donostia.eus; Secure; HTTPOnly",
    "Strict-Transport-Security": "max-age=16070400; includeSubDomains",
    "X-Content-Type-Options": "nosniff"
  },
  "scan_id": 32880295,
  "score": 0,
  "start_time": "Sun, 08 Jan 2023 01:07:04 GMT",
  "state": "FINISHED",
  "status_code": 200,
  "tests_failed": 4,
  "tests_passed": 8,
  "tests_quantity": 12
}