{
  "algorithm_version": 2,
  "end_time": "Tue, 10 Jan 2023 01:23:59 GMT",
  "grade": "F",
  "hidden": false,
  "likelihood_indicator": "MEDIUM",
  "response_headers": {
    "Content-Length": "41690",
    "Content-Type": "text/html",
    "Date": "Tue, 10 Jan 2023 01:23:57 GMT",
    "Feature-Policy": "microphone 'none'; usb 'none'; payment 'none'",
    "Set-Cookie": "TS011b0901=018ac16f67c7eb20b9f121c1fc15a9439ce26e33122cdedb92366e94e5ec102699157021b71fa240992b8f1481e36cad61e5b41db0; Path=/; Domain=.www.donostia.eus; Secure; HTTPOnly",
    "Strict-Transport-Security": "max-age=16070400; includeSubDomains",
    "X-Content-Type-Options": "nosniff"
  },
  "scan_id": 32962288,
  "score": 0,
  "start_time": "Tue, 10 Jan 2023 01:23:14 GMT",
  "state": "FINISHED",
  "status_code": 200,
  "tests_failed": 4,
  "tests_passed": 8,
  "tests_quantity": 12
}