{
  "algorithm_version": 2,
  "end_time": "Thu, 20 Oct 2022 00:20:07 GMT",
  "grade": "B",
  "hidden": false,
  "likelihood_indicator": "MEDIUM",
  "response_headers": {
    "Accept-Ranges": "bytes",
    "Connection": "Upgrade, Keep-Alive",
    "Content-Encoding": "gzip",
    "Content-Type": "text/html",
    "Date": "Thu, 20 Oct 2022 00:20:01 GMT",
    "Keep-Alive": "timeout=15, max=100",
    "Last-Modified": "Mon, 18 Apr 2022 08:21:00 GMT",
    "Referrer-Policy": "no-referrer-when-downgrade",
    "Set-Cookie": "visid_incap_171420=Ts9bUh15QTSnj9tBOmbsCi+UUGMAAAAAQUIPAAAAAAAOv9AMV5g/ghpU5gZsXfUq; expires=Thu, 19 Oct 2023 07:13:09 GMT; HttpOnly; path=/; Domain=.grancanaria.com; Secure; SameSite=None, nlbi_171420=YzAsYJGVHyYscCiA3tof+wAAAABLBtAsPJJBIubknBrSn8+x; path=/; Domain=.grancanaria.com; Secure; SameSite=None, incap_ses_569_171420=JGJxCTGD2zT7aS81O3/lBzGUUGMAAAAAsYIn9rEFafuYBewmcDOsTQ==; path=/; Domain=.grancanaria.com; Secure; SameSite=None",
    "Strict-Transport-Security": "max-age=31536000",
    "Transfer-Encoding": "chunked",
    "Upgrade": "h2",
    "Vary": "Accept-Encoding",
    "X-CDN": "Imperva",
    "X-Content-Type-Options": "nosniff",
    "X-Frame-Options": "SAMEORIGIN",
    "X-Iinfo": "6-30580754-30580756 NNNN CT(188 473 0) RT(1666225200535 41) q(0 0 7 0) r(9 9) U12",
    "X-XSS-Protection": "1; mode=block"
  },
  "scan_id": 30256217,
  "score": 70,
  "start_time": "Thu, 20 Oct 2022 00:19:55 GMT",
  "state": "FINISHED",
  "status_code": 200,
  "tests_failed": 2,
  "tests_passed": 10,
  "tests_quantity": 12
}