{
  "algorithm_version": 2,
  "end_time": "Tue, 31 Oct 2023 00:52:50 GMT",
  "grade": "F",
  "hidden": false,
  "likelihood_indicator": "MEDIUM",
  "response_headers": {
    "Cache-Control": "no-cache",
    "Connection": "keep-alive",
    "Content-Encoding": "gzip",
    "Content-Type": "text/html; charset=UTF-8",
    "Date": "Tue, 31 Oct 2023 00:52:46 GMT",
    "Expires": "Thu, 01 Jan 1970 00:00:01 GMT",
    "Referrer-Policy": "strict-origin-when-cross-origin",
    "Set-Cookie": "AWSALB=jq4pnnQO1sCYoK30TojVqEEo6OVKbBSeMicKcpEGBy1w/6ltzn1ZcRk0WmTsksqQOdptNnO4udcR7qzCI/yqE/4hi9lxu8fSX1br97YQbJwNU7V3Em8SVk2JcsI3; Expires=Tue, 07 Nov 2023 00:52:46 GMT; Path=/, AWSALBCORS=jq4pnnQO1sCYoK30TojVqEEo6OVKbBSeMicKcpEGBy1w/6ltzn1ZcRk0WmTsksqQOdptNnO4udcR7qzCI/yqE/4hi9lxu8fSX1br97YQbJwNU7V3Em8SVk2JcsI3; Expires=Tue, 07 Nov 2023 00:52:46 GMT; Path=/; SameSite=None; Secure",
    "Transfer-Encoding": "chunked",
    "Vary": "Accept-Encoding",
    "X-Content-Type-Options": "nosniff",
    "X-FastCGI-Cache": "HIT",
    "X-FastCGI-Zone": "cache_cartv_sm",
    "X-XSS-Protection": "1; mode=block"
  },
  "scan_id": 43839957,
  "score": 0,
  "start_time": "Tue, 31 Oct 2023 00:52:43 GMT",
  "state": "FINISHED",
  "status_code": 200,
  "tests_failed": 5,
  "tests_passed": 7,
  "tests_quantity": 12
}